arxml_parse/__init__.py
arxml_parse/io.py
arxml_parse/py.typed
arxml_parse/autosar_00042/__init__.py
arxml_parse/autosar_00042/autosar_00042.py
arxml_parse/autosar_00043/__init__.py
arxml_parse/autosar_00043/autosar_00043.py
arxml_parse/autosar_00044/__init__.py
arxml_parse/autosar_00044/autosar_00044.py
arxml_parse/autosar_00045/__init__.py
arxml_parse/autosar_00045/autosar_00045.py
arxml_parse/autosar_00046/__init__.py
arxml_parse/autosar_00046/autosar_00046.py
arxml_parse/autosar_00047/__init__.py
arxml_parse/autosar_00047/autosar_00047.py
arxml_parse/autosar_00048/__init__.py
arxml_parse/autosar_00048/autosar_00048.py
arxml_parse/autosar_00049/__init__.py
arxml_parse/autosar_00049/autosar_00049.py
arxml_parse/autosar_00050/__init__.py
arxml_parse/autosar_00050/autosar_00050.py
arxml_parse/autosar_00051/__init__.py
arxml_parse/autosar_00051/autosar_00051.py
arxml_parse/autosar_00052/__init__.py
arxml_parse/autosar_00052/autosar_00052.py
arxml_parse-0.1.1.dist-info/LICENSE.txt
arxml_parse-0.1.1.dist-info/METADATA
arxml_parse-0.1.1.dist-info/WHEEL
arxml_parse-0.1.1.dist-info/top_level.txt
arxml_parse-0.1.1.dist-info/RECORD
