Metadata-Version: 2.1
Name: arxml-parse
Version: 0.1.1
Summary: ARXML parser
Author-email: Artur Drogunow <Artur.Drogunow@zf.com>
License: MIT
Project-URL: Issues, https://github.com/zariiii9003/arxml-parse/issues
Project-URL: Source, https://github.com/zariiii9003/arxml-parse
Project-URL: Homepage, https://github.com/zariiii9003/arxml-parse
Classifier: License :: OSI Approved :: MIT License
Classifier: Programming Language :: Python :: 3.11
Classifier: Programming Language :: Python :: 3.12
Classifier: Programming Language :: Python :: 3.13
Requires-Python: >=3.11
License-File: LICENSE.txt
Requires-Dist: xsdata>=24.11
